promptsdk/.env
promptsdk/README.md
promptsdk/__init__.py
promptsdk/prompts.py
promptsdk-0.1.3.dist-info/METADATA
promptsdk-0.1.3.dist-info/WHEEL
promptsdk-0.1.3.dist-info/RECORD
